pydbtimetools/__init__.py
pydbtimetools/date_util.py
pydbtimetools/mongo_util.py
pydbtimetools/mysql_util.py
pydbtimetools/redis_util.py
pydbtimetools/config/__init__.py
pydbtimetools/config/config-dev.yaml
pydbtimetools/config/config-test.yaml
pydbtimetools/config/config.py
pydbtimetools/config/config.yaml
pydbtimetools-1.0.0.dist-info/METADATA
pydbtimetools-1.0.0.dist-info/WHEEL
pydbtimetools-1.0.0.dist-info/top_level.txt
pydbtimetools-1.0.0.dist-info/RECORD
