Metadata-Version: 2.1
Name: pydbtimetools
Version: 1.0.0
Summary: A package for MySQL and MongoDB and Redis and Date utilities
Home-page: UNKNOWN
Author: zxw
Author-email: your@email.com
License: UNKNOWN
Platform: UNKNOWN
Requires-Python: >=3.6
Requires-Dist: DBUtils (>=3.0.3)
Requires-Dist: PyMySQL (>=1.0.2)
Requires-Dist: PyYAML (>=6.0)
Requires-Dist: loguru (>=0.7.0)
Requires-Dist: pandas (>=1.1.5)
Requires-Dist: redis (>=4.3.6)
Requires-Dist: pymongo (>=4.1.1)
